muzlin/__init__.py
muzlin/schema.py
muzlin/anomaly/__init__.py
muzlin/anomaly/cluster.py
muzlin/anomaly/detector.py
muzlin/anomaly/graph.py
muzlin/anomaly/utils.py
muzlin/encoders/__init__.py
muzlin/encoders/base.py
muzlin/encoders/bedrock.py
muzlin/encoders/cohere.py
muzlin/encoders/fastembed.py
muzlin/encoders/google.py
muzlin/encoders/huggingface.py
muzlin/encoders/mistral.py
muzlin/encoders/openai.py
muzlin/encoders/voyageai.py
muzlin/encoders/zure.py
muzlin/index/__init__.py
muzlin/index/base.py
muzlin/index/langchain.py
muzlin/index/llama_index.py
muzlin/utils/__init__.py
muzlin/utils/defaults.py
muzlin/utils/logger.py
muzlin-0.0.6.dist-info/LICENSE
muzlin-0.0.6.dist-info/METADATA
muzlin-0.0.6.dist-info/WHEEL
muzlin-0.0.6.dist-info/top_level.txt
muzlin-0.0.6.dist-info/RECORD
