Metadata-Version: 2.2
Name: muzlin
Version: 0.0.6
Summary: Muzlin: a filtering toolset for semantic machine learning
Author: Daniel Kulik
Maintainer: Daniel Kulik
License: MIT License
Project-URL: Homepage, https://github.com/KulikDM/muzlin
Project-URL: Repository, https://github.com/KulikDM/muzlin
Keywords: RAG,outlier-detection,filtering,retrieval,semantic,ML,LLM,NLP
Classifier: Development Status :: 4 - Beta
Classifier: Intended Audience :: Developers
Classifier: Intended Audience :: Customer Service
Classifier: Intended Audience :: Education
Classifier: Intended Audience :: Science/Research
Classifier: Intended Audience :: Telecommunications Industry
Classifier: License :: OSI Approved :: MIT License
Classifier: Programming Language :: Python :: 3
Classifier: Programming Language :: Python :: 3.8
Classifier: Programming Language :: Python :: 3.9
Classifier: Programming Language :: Python :: 3.10
Classifier: Programming Language :: Python :: 3.11
Classifier: Programming Language :: Python :: 3.12
Classifier: Topic :: Software Development
Classifier: Topic :: Software Development :: Embedded Systems
Classifier: Topic :: Communications :: Chat
Classifier: Topic :: Scientific/Engineering
Classifier: Topic :: Scientific/Engineering :: Artificial Intelligence
Classifier: Topic :: Text Processing
Classifier: Topic :: Text Processing :: Filters
Classifier: Topic :: Text Processing :: Indexing
Classifier: Operating System :: POSIX :: Linux
Classifier: Operating System :: MacOS
Classifier: Operating System :: Microsoft :: Windows
Requires-Python: >=3.8
License-File: LICENSE
Requires-Dist: apipkg
Requires-Dist: colorlog
Requires-Dist: joblib>=0.14.1
Requires-Dist: numpy<=1.26.4
Requires-Dist: pydantic>=2.0
Requires-Dist: pyod>=1.0.0
Requires-Dist: pythresh>=0.3.0
Requires-Dist: scikit-learn>=0.20.0
Requires-Dist: scipy>=1.3.1
Requires-Dist: umap-learn
Provides-Extra: dev
Requires-Dist: pytest; extra == "dev"
Requires-Dist: pytest-cov; extra == "dev"
Requires-Dist: pytest-mock; extra == "dev"
Requires-Dist: pytest-xdist; extra == "dev"
Requires-Dist: pytest-asyncio; extra == "dev"
Requires-Dist: requests-mock; extra == "dev"
Requires-Dist: flake8; extra == "dev"
Requires-Dist: mypy; extra == "dev"
Requires-Dist: typed-ast; extra == "dev"
Requires-Dist: pydocstringformatter; extra == "dev"
Requires-Dist: ruff; extra == "dev"
Requires-Dist: autopep8; extra == "dev"
Requires-Dist: isort; extra == "dev"
Requires-Dist: openai<2.0.0,>=1.10.0; extra == "dev"
Requires-Dist: cohere<6.00,>=5.00; extra == "dev"
Requires-Dist: voyageai; extra == "dev"
Requires-Dist: mistralai<1.0.0; extra == "dev"
Requires-Dist: boto3; extra == "dev"
Requires-Dist: botocore; extra == "dev"
Requires-Dist: fastembed; extra == "dev"
Requires-Dist: google-cloud-aiplatform; extra == "dev"
Requires-Dist: mlflow; extra == "dev"
Requires-Dist: huggingface-hub; extra == "dev"
Requires-Dist: torch; extra == "dev"
Requires-Dist: transformers; extra == "dev"
Requires-Dist: tokenizers; extra == "dev"
Requires-Dist: llama-index-embeddings-huggingface; extra == "dev"
Requires-Dist: llama-index; extra == "dev"
Requires-Dist: faiss-cpu; extra == "dev"
Requires-Dist: langchain-community; extra == "dev"
Requires-Dist: sentence-transformers; extra == "dev"
Requires-Dist: networkx; extra == "dev"
Requires-Dist: pygod; extra == "dev"
Requires-Dist: torch_geometric; extra == "dev"
Requires-Dist: torch_scatter; extra == "dev"
Requires-Dist: torch_sparse; extra == "dev"
Requires-Dist: torch_cluster; extra == "dev"
Requires-Dist: torch_spline_conv; extra == "dev"
Provides-Extra: graph
Requires-Dist: networkx; extra == "graph"
Requires-Dist: pygod; extra == "graph"
Requires-Dist: torch; extra == "graph"
Requires-Dist: torch_geometric; extra == "graph"
Requires-Dist: torch_scatter; extra == "graph"
Requires-Dist: torch_sparse; extra == "graph"
Requires-Dist: torch_cluster; extra == "graph"
Requires-Dist: torch_spline_conv; extra == "graph"
Provides-Extra: notebook
Requires-Dist: mlflow; extra == "notebook"
Requires-Dist: pandas; extra == "notebook"
Requires-Dist: faiss-cpu; extra == "notebook"
Requires-Dist: langchain-community; extra == "notebook"
Requires-Dist: sentence-transformers; extra == "notebook"
Requires-Dist: matplotlib; extra == "notebook"
Requires-Dist: plotly; extra == "notebook"
Requires-Dist: datasets; extra == "notebook"
Requires-Dist: huggingface-hub; extra == "notebook"
Requires-Dist: torch; extra == "notebook"
Requires-Dist: transformers; extra == "notebook"
Requires-Dist: tokenizers; extra == "notebook"
Requires-Dist: pygod; extra == "notebook"
Requires-Dist: torch_geometric; extra == "notebook"
